plover_touchscreen_stenotype/Main.py
plover_touchscreen_stenotype/NoneMachine.py
plover_touchscreen_stenotype/__init__.py
plover_touchscreen_stenotype/settings.py
plover_touchscreen_stenotype/lib/Joystick.py
plover_touchscreen_stenotype/lib/UseDpi.py
plover_touchscreen_stenotype/lib/constants.py
plover_touchscreen_stenotype/lib/reactivity.py
plover_touchscreen_stenotype/lib/types.py
plover_touchscreen_stenotype/lib/util.py
plover_touchscreen_stenotype/lib/keyboard_layout/LayoutDescriptor.py
plover_touchscreen_stenotype/lib/keyboard_layout/descriptors/__init__.py
plover_touchscreen_stenotype/lib/keyboard_layout/descriptors/common.py
plover_touchscreen_stenotype/lib/keyboard_layout/descriptors/english_stenotype_amphitheory.py
plover_touchscreen_stenotype/lib/keyboard_layout/descriptors/english_stenotype_ireland.py
plover_touchscreen_stenotype/lib/keyboard_layout/descriptors/english_stenotype_lapwing.py
plover_touchscreen_stenotype/lib/keyboard_layout/descriptors/english_velotype.py
plover_touchscreen_stenotype/widgets/CenterControls.py
plover_touchscreen_stenotype/widgets/DisplayAlignmentLayout.py
plover_touchscreen_stenotype/widgets/FloatInput.py
plover_touchscreen_stenotype/widgets/KeyWidget.py
plover_touchscreen_stenotype/widgets/KeyboardWidget.py
plover_touchscreen_stenotype/widgets/RotatableKeyContainer.py
plover_touchscreen_stenotype/widgets/SettingsDialog.py
plover_touchscreen_stenotype/widgets/StrokePreview.py
plover_touchscreen_stenotype/widgets/__init__.py
plover_touchscreen_stenotype/widgets/build_keyboard.py
plover_touchscreen_stenotype/widgets/build_keyboard_config/english_stenotype.py
plover_touchscreen_stenotype/widgets/build_keyboard_config/stenotype_extended_custom.py
plover_touchscreen_stenotype/widgets/composables/UseDpi.py
plover_touchscreen_stenotype/widgets/composables/UseJoystickControl.py
plover_touchscreen_stenotype/widgets/joysticks/JoysticksWidget.py
plover_touchscreen_stenotype/widgets/keyboard/GroupObject.py
plover_touchscreen_stenotype-0.3.0b0.dist-info/METADATA
plover_touchscreen_stenotype-0.3.0b0.dist-info/WHEEL
plover_touchscreen_stenotype-0.3.0b0.dist-info/entry_points.txt
plover_touchscreen_stenotype-0.3.0b0.dist-info/top_level.txt
plover_touchscreen_stenotype-0.3.0b0.dist-info/zip-safe
plover_touchscreen_stenotype-0.3.0b0.dist-info/RECORD
