Metadata-Version: 2.1
Name: plover-touchscreen-stenotype
Version: 0.3.0b0
Summary: Touchscreen stenotype that utilizes multi-touch
Keywords: plover plover_plugin
Classifier: Development Status :: 4 - Beta
Classifier: Environment :: Plugins
Classifier: Intended Audience :: End Users/Desktop
Classifier: Programming Language :: Python :: 3
Classifier: Programming Language :: Python :: 3.10
Requires-Dist: plover[gui_qt] >=4.0.0.dev12
Requires-Dist: pywin32 >=304.0.0 ; platform_system == "Windows"
